queclinkdoc/__init__.py
queclinkdoc/_version.py
queclinkdoc/layout.html
queclinkdoc/theme.conf
queclinkdoc/static/custom.css
queclinkdoc/static/queclinkdoc.css_t
queclinkdoc/static/queclinkdoc_a0.95em.js_t
queclinkdoc/static/queclinkdoc_head.js_t
queclinkdoc/static/queclinkdoc_last.js_t
queclinkdoc/static/queclinkdoc_toc.js_t
queclinkdoc/static/searchimg.png
queclinkdoc-2.2.dist-info/LICENSE
queclinkdoc-2.2.dist-info/METADATA
queclinkdoc-2.2.dist-info/WHEEL
queclinkdoc-2.2.dist-info/entry_points.txt
queclinkdoc-2.2.dist-info/top_level.txt
queclinkdoc-2.2.dist-info/RECORD
