Metadata-Version: 2.1
Name: queclinkdoc
Version: 2.2
Summary: A simple, clean, friendly, and less-configured Sphinx theme
Home-page: https://github.com/Queclink-Open-Software-Store/queclinkdoc
Author: Queclink Wireless Solutions Co., Ltd.
Author-email: Hubert.Lee@queclink.com
License-File: LICENSE
